MANIFEST.in
README.rst
ez_setup.py
mayloop
setup.py
mayloop/__init__.py
mayloop/config.py
mayloop/exc.py
mayloop/limits.py
mayloop/logger.py
mayloop/mainloop.py
mayloop/select_call.py
mayloop/stats.py
mayloop/version.py
mayloop.egg-info/PKG-INFO
mayloop.egg-info/SOURCES.txt
mayloop.egg-info/dependency_links.txt
mayloop.egg-info/requires.txt
mayloop.egg-info/top_level.txt
mayloop/factory/__init__.py
mayloop/factory/telnet_server_factory.py
mayloop/imported/__init__.py
mayloop/imported/twisted/__init__.py
mayloop/imported/twisted/internet_interfaces.py
mayloop/imported/twisted/internet_protocol.py
mayloop/protocol/__init__.py
mayloop/protocol/blocking_fixed_length_message.py
mayloop/protocol/fixed_length_message.py
mayloop/protocol/line_message.py
mayloop/protocol/message.py
mayloop/protocol/telnet_server.py
mayloop/test/__init__.py
mayloop/test/mock_client.py
mayloop/test/mock_protocols.py
mayloop/test/start_server.py
mayloop/test/test_mainloop.py
mayloop/transport/__init__.py
mayloop/transport/address.py
mayloop/transport/pipe_connection.py
mayloop/transport/tcp_connection.py